README.md
setup.cfg
setup.py
Binomial_Gauss/Binomialdistribution.py
Binomial_Gauss/Gaussiandistribution.py
Binomial_Gauss/Generaldistribution.py
Binomial_Gauss/__init__.py
Binomial_Gauss.egg-info/PKG-INFO
Binomial_Gauss.egg-info/SOURCES.txt
Binomial_Gauss.egg-info/dependency_links.txt
Binomial_Gauss.egg-info/not-zip-safe
Binomial_Gauss.egg-info/top_level.txt