Metadata-Version: 1.0
Name: Binomial-Gauss
Version: 1.1
Summary: Gaussian and Binomial distributions
Home-page: UNKNOWN
Author: Pankaj Biradar
Author-email: pankaj28988@gmail.com
License: UNKNOWN
Platform: UNKNOWN
